delune/__init__.py
delune/_delune.cp35-win_amd64.pyd
delune/binfile.py
delune/colsetup.py
delune/docqueue.py
delune/filesystem.py
delune/language.py
delune/memory.py
delune/pthreadVC2.dll
delune/__pycache__/__init__.cpython-35.pyc
delune/analyzers/__init__.py
delune/analyzers/abstractAnalyzer.py
delune/analyzers/mecabKAnalyzer.py
delune/analyzers/standardAnalyzer.py
delune/analyzers/__pycache__/__init__.cpython-35.pyc
delune/analyzers/__pycache__/standardAnalyzer.cpython-35.pyc
delune/analyzers/util/__init__.py
delune/analyzers/util/htmlstrip.py
delune/classifier/__init__.py
delune/classifier/classifier.py
delune/classifier/classifieratdisk.py
delune/classifier/classifierservice.py
delune/classifier/featureselect.py
delune/classifier/gac.py
delune/classifier/labeld_document.py
delune/classifier/model.py
delune/classifier/trainer.py
delune/classifier/classifiers/__init__.py
delune/classifier/classifiers/featurevote.py
delune/classifier/classifiers/metaclassifier.py
delune/classifier/classifiers/multipath.py
delune/classifier/classifiers/naivebayes.py
delune/classifier/classifiers/rocchino.py
delune/classifier/classifiers/similarity.py
delune/classifier/classifiers/termcluster.py
delune/classifier/classifiers/tfidf.py
delune/classifier/segment/__init__.py
delune/classifier/segment/composedsegmentreader.py
delune/classifier/segment/composedsegmentwriter.py
delune/classifier/segment/segment.py
delune/cluster/__init__.py
delune/cluster/termCluster.py
delune/export/skitai/__export__.py
delune/export/skitai/__init__.py
delune/export/skitai/app-example.py
delune/export/skitai/app.py
delune/export/skitai/delune.py
delune/export/skitai/bin/indexer.py
delune/export/skitai/bin/mirror.py
delune/export/skitai/package/indexer.py
delune/export/skitai/package/mirror.py
delune/extension/delune/capsulethunk.h
delune/extension/delune/compile.sh
delune/extension/delune/compile32.cmd
delune/extension/delune/compile64.cmd
delune-0.3.1.7.dist-info/DESCRIPTION.rst
delune-0.3.1.7.dist-info/METADATA
delune-0.3.1.7.dist-info/RECORD
delune-0.3.1.7.dist-info/WHEEL
delune-0.3.1.7.dist-info/metadata.json
delune-0.3.1.7.dist-info/top_level.txt
