Metadata-Version: 2.0
Name: delune
Version: 0.3.1.7
Summary: DeLune Python Object Storage and Search Engine
Home-page: https://gitlab.com/hansroh/delune
Author: Hans Roh
Author-email: hansroh@gmail.com
License: GPLv3
Download-URL: https://pypi.python.org/pypi/delune
Platform: posix
Platform: nt
Classifier: License :: OSI Approved :: GNU General Public License v3 (GPLv3)
Classifier: Development Status :: 3 - Alpha
Classifier: Environment :: Console
Classifier: Topic :: Software Development :: Libraries :: Python Modules
Classifier: Intended Audience :: Developers
Classifier: Intended Audience :: Science/Research
Classifier: Programming Language :: Python
Classifier: Programming Language :: Python :: 3
Classifier: Topic :: Text Processing :: Indexing
